mermaid_mcp/__init__.py
mermaid_mcp/chart_info.py
mermaid_mcp/cli.py
mermaid_mcp/entry.py
mermaid_mcp/server.py
mermaid_mcp/utils.py
mermaid_mcp-0.1.2.dist-info/licenses/LICENSE
mermaid_mcp-0.1.2.dist-info/METADATA
mermaid_mcp-0.1.2.dist-info/WHEEL
mermaid_mcp-0.1.2.dist-info/entry_points.txt
mermaid_mcp-0.1.2.dist-info/top_level.txt
mermaid_mcp-0.1.2.dist-info/RECORD
