Metadata-Version: 2.4
Name: mermaid-mcp
Version: 0.1.2
Summary: Python model context protocol(MCP) server for mermaid
Requires-Python: >=3.10
License-File: LICENSE
Requires-Dist: httpx>=0.28.1
Requires-Dist: mcp>=1.8.1
Requires-Dist: fastapi>=0.110.0
Requires-Dist: uvicorn>=0.27.1
Requires-Dist: pydantic>=2.6.3
Requires-Dist: python-dotenv>=1.0.1
Requires-Dist: python-multipart>=0.0.9
Dynamic: license-file
